mag/__init__.py
mag/mag.py
magit-0.1.0.dist-info/LICENSE
magit-0.1.0.dist-info/WHEEL
magit-0.1.0.dist-info/METADATA
magit-0.1.0.dist-info/RECORD
