Metadata-Version: 2.1
Name: magit
Version: 0.1.0
Summary: Multi repo Git manager
Author: Pavel Brodsky
Author-email: pavel.brodsky@forter.com
Requires-Python: >=2.7,<3.0
Classifier: Programming Language :: Python :: 2
Classifier: Programming Language :: Python :: 2.7
